MANIFEST.in
requirements.txt
setup.cfg
setup.py
youtube/__init__.py
youtube/api.py
youtube/exceptions.py
youtube_python_sdk.egg-info/PKG-INFO
youtube_python_sdk.egg-info/SOURCES.txt
youtube_python_sdk.egg-info/dependency_links.txt
youtube_python_sdk.egg-info/requires.txt
youtube_python_sdk.egg-info/top_level.txt